{
    "file_version": 1,
    "quiz_type": "grammar_galaxy",
    "last_updated": "2026-04-28",
    "stages": [
        {
            "stage_number": 1,
            "title": "Novice",
            "level": "L1",
            "description": "Basic grammar: articles, tenses, plurals, simple vocab.",
            "question_types_in_stage": [
                "fill_in_blank",
                "synonym",
                "antonym",
                "plural",
                "spot_error",
                "past_tense"
            ],
            "questions": [
                {"id": "gg_s1_antonym_001", "type": "antonym", "question": "What is the opposite of 'yes'?", "options": ["okay", "maybe", "never", "no"], "answer_index": 3, "difficulty": "L1"},
                {"id": "gg_s1_past_tense_002", "type": "past_tense", "question": "What is the past tense of 'sing'?", "options": ["sings", "singed", "sang", "sung"], "answer_index": 2, "difficulty": "L1"},
                {"id": "gg_s1_antonym_003", "type": "antonym", "question": "What is the opposite of 'hot'?", "options": ["warm", "mild", "cool", "cold"], "answer_index": 3, "difficulty": "L1"},
                {"id": "gg_s1_fill_in_blank_004", "type": "fill_in_blank", "question": "He _____ very fast.", "options": ["run", "running", "runs", "ran"], "answer_index": 2, "difficulty": "L1"},
                {"id": "gg_s1_plural_005", "type": "plural", "question": "What is the plural of 'knife'?", "options": ["knifes", "knifes", "knivess", "knives"], "answer_index": 3, "difficulty": "L1"},
                {"id": "gg_s1_antonym_006", "type": "antonym", "question": "What is the opposite of 'big'?", "options": ["tall", "long", "wide", "small"], "answer_index": 3, "difficulty": "L1"},
                {"id": "gg_s1_fill_in_blank_007", "type": "fill_in_blank", "question": "I like to read _____ books.", "options": ["interestingly", "interest", "interesting", "interested"], "answer_index": 2, "difficulty": "L1"},
                {"id": "gg_s1_spot_error_008", "type": "spot_error", "question": "Find the error: 'She don't like mangoes.'", "options": ["She → Her", "mangoes → mango", "don't → doesn't", "like → likes"], "answer_index": 2, "difficulty": "L1"},
                {"id": "gg_s1_fill_in_blank_009", "type": "fill_in_blank", "question": "The dog _____ loudly at night.", "options": ["barks", "barking", "bark", "barked"], "answer_index": 0, "difficulty": "L1"},
                {"id": "gg_s1_spot_error_010", "type": "spot_error", "question": "Find the error: 'I has a pet dog.'", "options": ["pet → pets", "dog → dogs", "has → have", "I → Me"], "answer_index": 2, "difficulty": "L1"},
                {"id": "gg_s1_fill_in_blank_011", "type": "fill_in_blank", "question": "She put the book _____ the shelf.", "options": ["at", "in", "by", "on"], "answer_index": 3, "difficulty": "L1"},
                {"id": "gg_s1_spot_error_012", "type": "spot_error", "question": "Find the error: 'The boys plays football.'", "options": ["football → footballs", "boys → boy", "The → A", "plays → play"], "answer_index": 3, "difficulty": "L1"},
                {"id": "gg_s1_plural_013", "type": "plural", "question": "What is the plural of 'child'?", "options": ["childrens", "childs", "children", "childes"], "answer_index": 2, "difficulty": "L1"},
                {"id": "gg_s1_spot_error_014", "type": "spot_error", "question": "Find the error: 'The birds flied away.'", "options": ["birds → bird", "away → aside", "The → A", "flied → flew"], "answer_index": 3, "difficulty": "L1"},
                {"id": "gg_s1_plural_015", "type": "plural", "question": "What is the plural of 'mouse'?", "options": ["mice", "mouses", "mousey", "mices"], "answer_index": 0, "difficulty": "L1"},
                {"id": "gg_s1_antonym_016", "type": "antonym", "question": "What is the opposite of 'wet'?", "options": ["moist", "dry", "humid", "damp"], "answer_index": 1, "difficulty": "L1"},
                {"id": "gg_s1_past_tense_017", "type": "past_tense", "question": "What is the past tense of 'eat'?", "options": ["eaten", "aten", "eated", "ate"], "answer_index": 3, "difficulty": "L1"},
                {"id": "gg_s1_antonym_018", "type": "antonym", "question": "What is the opposite of 'clean'?", "options": ["dusty", "messy", "dirty", "muddy"], "answer_index": 2, "difficulty": "L1"},
                {"id": "gg_s1_spot_error_019", "type": "spot_error", "question": "Find the error: 'My mother make delicious food.'", "options": ["food → foods", "delicious → deliciously", "My → Mine", "make → makes"], "answer_index": 3, "difficulty": "L1"},
                {"id": "gg_s1_antonym_020", "type": "antonym", "question": "What is the opposite of 'full'?", "options": ["empty", "hollow", "blank", "bare"], "answer_index": 0, "difficulty": "L1"},
                {"id": "gg_s1_synonym_021", "type": "synonym", "question": "Which word means the same as 'sick'?", "options": ["ill", "fit", "strong", "healthy"], "answer_index": 0, "difficulty": "L1"},
                {"id": "gg_s1_past_tense_022", "type": "past_tense", "question": "What is the past tense of 'drink'?", "options": ["drank", "drinks", "drinked", "drunk"], "answer_index": 0, "difficulty": "L1"},
                {"id": "gg_s1_synonym_023", "type": "synonym", "question": "Which word means the same as 'fast'?", "options": ["slow", "quiet", "lazy", "quick"], "answer_index": 3, "difficulty": "L1"},
                {"id": "gg_s1_spot_error_024", "type": "spot_error", "question": "Find the error: 'The cat eated all the fish.'", "options": ["cat → cats", "fish → fishes", "eated → ate", "The → A"], "answer_index": 2, "difficulty": "L1"},
                {"id": "gg_s1_synonym_025", "type": "synonym", "question": "Which word means the same as 'sad'?", "options": ["brave", "unhappy", "excited", "loud"], "answer_index": 1, "difficulty": "L1"},
                {"id": "gg_s1_antonym_026", "type": "antonym", "question": "What is the opposite of 'tall'?", "options": ["thin", "weak", "short", "small"], "answer_index": 2, "difficulty": "L1"},
                {"id": "gg_s1_spot_error_027", "type": "spot_error", "question": "Find the error: 'He go to school every day.'", "options": ["every → each", "to → at", "He → His", "go → goes"], "answer_index": 3, "difficulty": "L1"},
                {"id": "gg_s1_synonym_028", "type": "synonym", "question": "Which word means the same as 'pretty'?", "options": ["ugly", "dull", "beautiful", "plain"], "answer_index": 2, "difficulty": "L1"},
                {"id": "gg_s1_past_tense_029", "type": "past_tense", "question": "What is the past tense of 'fall'?", "options": ["falls", "fallen", "fell", "falled"], "answer_index": 2, "difficulty": "L1"},
                {"id": "gg_s1_synonym_030", "type": "synonym", "question": "Which word means the same as 'brave'?", "options": ["courageous", "cowardly", "scared", "weak"], "answer_index": 0, "difficulty": "L1"},
                {"id": "gg_s1_fill_in_blank_031", "type": "fill_in_blank", "question": "This is _____ easy question.", "options": ["the", "an", "some", "a"], "answer_index": 1, "difficulty": "L1"},
                {"id": "gg_s1_antonym_032", "type": "antonym", "question": "What is the opposite of 'start'?", "options": ["end", "wait", "stop", "pause"], "answer_index": 0, "difficulty": "L1"},
                {"id": "gg_s1_plural_033", "type": "plural", "question": "What is the plural of 'woman'?", "options": ["women", "womans", "womens", "woman's"], "answer_index": 0, "difficulty": "L1"},
                {"id": "gg_s1_spot_error_034", "type": "spot_error", "question": "Find the error: 'We was at home yesterday.'", "options": ["We → Us", "yesterday → today", "was → were", "at → in"], "answer_index": 2, "difficulty": "L1"},
                {"id": "gg_s1_plural_035", "type": "plural", "question": "What is the plural of 'flower'?", "options": ["floweres", "floweris", "flowers", "flower's"], "answer_index": 2, "difficulty": "L1"},
                {"id": "gg_s1_antonym_036", "type": "antonym", "question": "What is the opposite of 'happy'?", "options": ["tired", "bored", "shy", "sad"], "answer_index": 3, "difficulty": "L1"},
                {"id": "gg_s1_past_tense_037", "type": "past_tense", "question": "What is the past tense of 'sit'?", "options": ["sitted", "sat", "sit", "sits"], "answer_index": 1, "difficulty": "L1"},
                {"id": "gg_s1_plural_038", "type": "plural", "question": "What is the plural of 'bus'?", "options": ["buses", "busies", "buss", "bus's"], "answer_index": 0, "difficulty": "L1"},
                {"id": "gg_s1_past_tense_039", "type": "past_tense", "question": "What is the past tense of 'think'?", "options": ["thinked", "thought", "thinks", "think"], "answer_index": 1, "difficulty": "L1"},
                {"id": "gg_s1_fill_in_blank_040", "type": "fill_in_blank", "question": "There is _____ apple on the table.", "options": ["some", "a", "the", "an"], "answer_index": 3, "difficulty": "L1"},
                {"id": "gg_s1_antonym_041", "type": "antonym", "question": "What is the opposite of 'love'?", "options": ["admire", "like", "hate", "enjoy"], "answer_index": 2, "difficulty": "L1"},
                {"id": "gg_s1_synonym_042", "type": "synonym", "question": "Which word means the same as 'look'?", "options": ["touch", "hear", "see", "taste"], "answer_index": 2, "difficulty": "L1"},
                {"id": "gg_s1_antonym_043", "type": "antonym", "question": "What is the opposite of 'fast'?", "options": ["smooth", "quick", "steady", "slow"], "answer_index": 3, "difficulty": "L1"},
                {"id": "gg_s1_synonym_044", "type": "synonym", "question": "Which word means the same as 'tired'?", "options": ["strong", "sleepy", "fresh", "active"], "answer_index": 1, "difficulty": "L1"},
                {"id": "gg_s1_antonym_045", "type": "antonym", "question": "What is the opposite of 'day'?", "options": ["morning", "night", "dusk", "noon"], "answer_index": 1, "difficulty": "L1"},
                {"id": "gg_s1_plural_046", "type": "plural", "question": "What is the plural of 'sheep'?", "options": ["sheepes", "sheep", "sheepes", "sheeps"], "answer_index": 1, "difficulty": "L1"},
                {"id": "gg_s1_fill_in_blank_047", "type": "fill_in_blank", "question": "She _____ very happy today.", "options": ["be", "are", "am", "is"], "answer_index": 3, "difficulty": "L1"},
                {"id": "gg_s1_plural_048", "type": "plural", "question": "What is the plural of 'baby'?", "options": ["babys", "babiess", "babies", "baby's"], "answer_index": 2, "difficulty": "L1"},
                {"id": "gg_s1_antonym_049", "type": "antonym", "question": "What is the opposite of 'open'?", "options": ["lost", "closed", "broken", "empty"], "answer_index": 1, "difficulty": "L1"},
                {"id": "gg_s1_plural_050", "type": "plural", "question": "What is the plural of 'city'?", "options": ["citys", "cityes", "city's", "cities"], "answer_index": 3, "difficulty": "L1"},
                {"id": "gg_s1_past_tense_051", "type": "past_tense", "question": "What is the past tense of 'see'?", "options": ["sawed", "seen", "seed", "saw"], "answer_index": 3, "difficulty": "L1"},
                {"id": "gg_s1_antonym_052", "type": "antonym", "question": "What is the opposite of 'early'?", "options": ["slow", "after", "last", "late"], "answer_index": 3, "difficulty": "L1"},
                {"id": "gg_s1_fill_in_blank_053", "type": "fill_in_blank", "question": "They _____ to the park on weekends.", "options": ["go", "gone", "going", "goes"], "answer_index": 0, "difficulty": "L1"},
                {"id": "gg_s1_plural_054", "type": "plural", "question": "What is the plural of 'tooth'?", "options": ["teeth", "teeths", "toothes", "tooths"], "answer_index": 0, "difficulty": "L1"},
                {"id": "gg_s1_fill_in_blank_055", "type": "fill_in_blank", "question": "The children _____ in the playground.", "options": ["played", "play", "playing", "plays"], "answer_index": 1, "difficulty": "L1"},
                {"id": "gg_s1_antonym_056", "type": "antonym", "question": "What is the opposite of 'old'?", "options": ["young", "recent", "new", "fresh"], "answer_index": 0, "difficulty": "L1"},
                {"id": "gg_s1_plural_057", "type": "plural", "question": "What is the plural of 'box'?", "options": ["boxes", "boxs", "boxies", "box's"], "answer_index": 0, "difficulty": "L1"},
                {"id": "gg_s1_spot_error_058", "type": "spot_error", "question": "Find the error: 'He don't have a pencil.'", "options": ["He → His", "have → has", "pencil → pencils", "don't → doesn't"], "answer_index": 3, "difficulty": "L1"},
                {"id": "gg_s1_synonym_059", "type": "synonym", "question": "Which word means the same as 'small'?", "options": ["broad", "heavy", "huge", "little"], "answer_index": 3, "difficulty": "L1"},
                {"id": "gg_s1_plural_060", "type": "plural", "question": "What is the plural of 'wolf'?", "options": ["wolf's", "wolves", "wolfes", "wolfs"], "answer_index": 1, "difficulty": "L1"},
                {"id": "gg_s1_synonym_061", "type": "synonym", "question": "Which word means the same as 'walk'?", "options": ["run", "jump", "crawl", "stroll"], "answer_index": 3, "difficulty": "L1"},
                {"id": "gg_s1_fill_in_blank_062", "type": "fill_in_blank", "question": "They _____ friends since childhood.", "options": ["be", "am", "are", "is"], "answer_index": 2, "difficulty": "L1"},
                {"id": "gg_s1_plural_063", "type": "plural", "question": "What is the plural of 'book'?", "options": ["bookes", "book's", "books", "bookies"], "answer_index": 2, "difficulty": "L1"},
                {"id": "gg_s1_fill_in_blank_064", "type": "fill_in_blank", "question": "He _____ his homework every evening.", "options": ["does", "do", "did", "doing"], "answer_index": 0, "difficulty": "L1"},
                {"id": "gg_s1_spot_error_065", "type": "spot_error", "question": "Find the error: 'She are my best friend.'", "options": ["best → better", "are → is", "my → mine", "She → Her"], "answer_index": 1, "difficulty": "L1"},
                {"id": "gg_s1_synonym_066", "type": "synonym", "question": "Which word means the same as 'thin'?", "options": ["tall", "fat", "slim", "wide"], "answer_index": 2, "difficulty": "L1"},
                {"id": "gg_s1_spot_error_067", "type": "spot_error", "question": "Find the error: 'She goed to the market.'", "options": ["She → Her", "to → at", "goed → went", "market → markets"], "answer_index": 2, "difficulty": "L1"},
                {"id": "gg_s1_antonym_068", "type": "antonym", "question": "What is the opposite of 'brave'?", "options": ["quiet", "timid", "shy", "cowardly"], "answer_index": 3, "difficulty": "L1"},
                {"id": "gg_s1_past_tense_069", "type": "past_tense", "question": "What is the past tense of 'take'?", "options": ["took", "takes", "taken", "taked"], "answer_index": 0, "difficulty": "L1"},
                {"id": "gg_s1_synonym_070", "type": "synonym", "question": "Which word means the same as 'smart'?", "options": ["dull", "clever", "lazy", "weak"], "answer_index": 1, "difficulty": "L1"},
                {"id": "gg_s1_fill_in_blank_071", "type": "fill_in_blank", "question": "He drinks _____ cup of tea every morning.", "options": ["the", "an", "no article", "a"], "answer_index": 3, "difficulty": "L1"},
                {"id": "gg_s1_past_tense_072", "type": "past_tense", "question": "What is the past tense of 'break'?", "options": ["broken", "breaks", "broke", "breaked"], "answer_index": 2, "difficulty": "L1"},
                {"id": "gg_s1_plural_073", "type": "plural", "question": "What is the plural of 'ox'?", "options": ["oxs", "ox's", "oxen", "oxes"], "answer_index": 2, "difficulty": "L1"},
                {"id": "gg_s1_past_tense_074", "type": "past_tense", "question": "What is the past tense of 'write'?", "options": ["writed", "wrote", "writes", "written"], "answer_index": 1, "difficulty": "L1"},
                {"id": "gg_s1_plural_075", "type": "plural", "question": "What is the plural of 'foot'?", "options": ["footies", "feet", "foots", "feets"], "answer_index": 1, "difficulty": "L1"},
                {"id": "gg_s1_past_tense_076", "type": "past_tense", "question": "What is the past tense of 'speak'?", "options": ["speaked", "speaks", "spoken", "spoke"], "answer_index": 3, "difficulty": "L1"},
                {"id": "gg_s1_synonym_077", "type": "synonym", "question": "Which word means the same as 'happy'?", "options": ["angry", "scared", "tired", "joyful"], "answer_index": 3, "difficulty": "L1"},
                {"id": "gg_s1_spot_error_078", "type": "spot_error", "question": "Find the error: 'She have two brothers.'", "options": ["She → Her", "two → to", "brothers → brother", "have → has"], "answer_index": 3, "difficulty": "L1"},
                {"id": "gg_s1_past_tense_079", "type": "past_tense", "question": "What is the past tense of 'bring'?", "options": ["brought", "bringed", "brang", "brings"], "answer_index": 0, "difficulty": "L1"},
                {"id": "gg_s1_spot_error_080", "type": "spot_error", "question": "Find the error: 'He runned very fast.'", "options": ["very → too", "runned → ran", "fast → faster", "He → His"], "answer_index": 1, "difficulty": "L1"},
                {"id": "gg_s1_plural_081", "type": "plural", "question": "What is the plural of 'man'?", "options": ["manes", "men", "man's", "mans"], "answer_index": 1, "difficulty": "L1"},
                {"id": "gg_s1_synonym_082", "type": "synonym", "question": "Which word means the same as 'cold'?", "options": ["chilly", "hot", "warm", "bright"], "answer_index": 0, "difficulty": "L1"},
                {"id": "gg_s1_past_tense_083", "type": "past_tense", "question": "What is the past tense of 'buy'?", "options": ["bought", "buys", "buyed", "buy"], "answer_index": 0, "difficulty": "L1"},
                {"id": "gg_s1_synonym_084", "type": "synonym", "question": "Which word means the same as 'big'?", "options": ["short", "soft", "large", "tiny"], "answer_index": 2, "difficulty": "L1"},
                {"id": "gg_s1_past_tense_085", "type": "past_tense", "question": "What is the past tense of 'find'?", "options": ["founds", "find", "found", "finded"], "answer_index": 2, "difficulty": "L1"},
                {"id": "gg_s1_fill_in_blank_086", "type": "fill_in_blank", "question": "She drinks _____ glass of water every morning.", "options": ["an", "no article", "a", "the"], "answer_index": 2, "difficulty": "L1"},
                {"id": "gg_s1_plural_087", "type": "plural", "question": "What is the plural of 'cat'?", "options": ["cates", "cats", "cat's", "caties"], "answer_index": 1, "difficulty": "L1"},
                {"id": "gg_s1_spot_error_088", "type": "spot_error", "question": "Find the error: 'I am knowing the answer.'", "options": ["I → Me", "answer → answers", "the → a", "am knowing → know"], "answer_index": 3, "difficulty": "L1"},
                {"id": "gg_s1_fill_in_blank_089", "type": "fill_in_blank", "question": "We _____ to school every day.", "options": ["going", "went", "go", "goes"], "answer_index": 2, "difficulty": "L1"},
                {"id": "gg_s1_spot_error_090", "type": "spot_error", "question": "Find the error: 'They is playing cricket.'", "options": ["playing → plays", "is → are", "cricket → crickets", "They → Them"], "answer_index": 1, "difficulty": "L1"},
                {"id": "gg_s1_past_tense_091", "type": "past_tense", "question": "What is the past tense of 'swim'?", "options": ["swims", "swam", "swimmed", "swum"], "answer_index": 1, "difficulty": "L1"},
                {"id": "gg_s1_fill_in_blank_092", "type": "fill_in_blank", "question": "I have _____ umbrella with me today.", "options": ["some", "the", "a", "an"], "answer_index": 3, "difficulty": "L1"},
                {"id": "gg_s1_synonym_093", "type": "synonym", "question": "Which word means the same as 'afraid'?", "options": ["calm", "brave", "scared", "bold"], "answer_index": 2, "difficulty": "L1"},
                {"id": "gg_s1_antonym_094", "type": "antonym", "question": "What is the opposite of 'give'?", "options": ["take", "hold", "lose", "keep"], "answer_index": 0, "difficulty": "L1"},
                {"id": "gg_s1_synonym_095", "type": "synonym", "question": "Which word means the same as 'speak'?", "options": ["talk", "write", "read", "listen"], "answer_index": 0, "difficulty": "L1"},
                {"id": "gg_s1_past_tense_096", "type": "past_tense", "question": "What is the past tense of 'go'?", "options": ["goed", "went", "gone", "goes"], "answer_index": 1, "difficulty": "L1"},
                {"id": "gg_s1_synonym_097", "type": "synonym", "question": "Which word means the same as 'begin'?", "options": ["finish", "wait", "stop", "start"], "answer_index": 3, "difficulty": "L1"},
                {"id": "gg_s1_fill_in_blank_098", "type": "fill_in_blank", "question": "I _____ a student.", "options": ["is", "be", "are", "am"], "answer_index": 3, "difficulty": "L1"},
                {"id": "gg_s1_spot_error_099", "type": "spot_error", "question": "Find the error: 'They is playing cricket.'", "options": ["cricket → crickets", "They → Them", "is → are", "playing → plays"], "answer_index": 2, "difficulty": "L1"},
                {"id": "gg_s1_fill_in_blank_100", "type": "fill_in_blank", "question": "My mother _____ very well.", "options": ["cooking", "cook", "cooked", "cooks"], "answer_index": 3, "difficulty": "L1"}
            ]
        },
        {
            "stage_number": 2,
            "title": "Intermediate",
            "level": "L2",
            "description": "Intermediate grammar: continuous tenses, comparative adjectives, tricky prepositions, and irregular plurals.",
            "question_types_in_stage": [
                "fill_in_blank",
                "synonym",
                "antonym",
                "plural",
                "spot_error",
                "past_tense"
            ],
            "questions": [
                {"id": "gg_s2_fill_in_blank_001", "type": "fill_in_blank", "question": "She is much _____ than her brother.", "options": ["tallest", "taller", "tall", "more tall"], "answer_index": 1, "difficulty": "L2"},
                {"id": "gg_s2_fill_in_blank_002", "type": "fill_in_blank", "question": "We are going on vacation _____ July.", "options": ["by", "on", "in", "at"], "answer_index": 2, "difficulty": "L2"},
                {"id": "gg_s2_fill_in_blank_003", "type": "fill_in_blank", "question": "The meeting is scheduled _____ Monday morning.", "options": ["for", "at", "in", "on"], "answer_index": 3, "difficulty": "L2"},
                {"id": "gg_s2_fill_in_blank_004", "type": "fill_in_blank", "question": "He has been very good _____ math since childhood.", "options": ["at", "with", "in", "on"], "answer_index": 0, "difficulty": "L2"},
                {"id": "gg_s2_fill_in_blank_005", "type": "fill_in_blank", "question": "I have _____ waiting for the bus for an hour.", "options": ["be", "was", "being", "been"], "answer_index": 3, "difficulty": "L2"},
                {"id": "gg_s2_fill_in_blank_006", "type": "fill_in_blank", "question": "They _____ playing football when it started to rain.", "options": ["are", "were", "have", "was"], "answer_index": 1, "difficulty": "L2"},
                {"id": "gg_s2_fill_in_blank_007", "type": "fill_in_blank", "question": "He speaks French fluently, _____?", "options": ["isn't he", "does he", "doesn't he", "don't he"], "answer_index": 2, "difficulty": "L2"},
                {"id": "gg_s2_fill_in_blank_008", "type": "fill_in_blank", "question": "You must _____ your homework before dinner.", "options": ["did", "make", "doing", "do"], "answer_index": 3, "difficulty": "L2"},
                {"id": "gg_s2_fill_in_blank_009", "type": "fill_in_blank", "question": "_____ many apples are left in the basket?", "options": ["How", "What", "So", "Too"], "answer_index": 0, "difficulty": "L2"},
                {"id": "gg_s2_fill_in_blank_010", "type": "fill_in_blank", "question": "I don't have _____ money left in my wallet.", "options": ["some", "much", "many", "few"], "answer_index": 1, "difficulty": "L2"},
                {"id": "gg_s2_fill_in_blank_011", "type": "fill_in_blank", "question": "She has _____ to Paris twice this year.", "options": ["was", "gone", "been", "went"], "answer_index": 2, "difficulty": "L2"},
                {"id": "gg_s2_fill_in_blank_012", "type": "fill_in_blank", "question": "He is the _____ boy in the entire school.", "options": ["smart", "smarter", "most smart", "smartest"], "answer_index": 3, "difficulty": "L2"},
                {"id": "gg_s2_fill_in_blank_013", "type": "fill_in_blank", "question": "My new car is more _____ than my old one.", "options": ["expensive", "cost", "cheaper", "expensiver"], "answer_index": 0, "difficulty": "L2"},
                {"id": "gg_s2_fill_in_blank_014", "type": "fill_in_blank", "question": "I usually prefer drinking tea _____ coffee.", "options": ["over", "to", "than", "from"], "answer_index": 1, "difficulty": "L2"},
                {"id": "gg_s2_fill_in_blank_015", "type": "fill_in_blank", "question": "He sincerely apologized _____ his careless mistake.", "options": ["about", "to", "for", "on"], "answer_index": 2, "difficulty": "L2"},
                {"id": "gg_s2_fill_in_blank_016", "type": "fill_in_blank", "question": "She has always been afraid _____ spiders.", "options": ["by", "from", "with", "of"], "answer_index": 3, "difficulty": "L2"},
                {"id": "gg_s2_fill_in_blank_017", "type": "fill_in_blank", "question": "They are looking forward _____ meeting you tomorrow.", "options": ["to", "about", "for", "at"], "answer_index": 0, "difficulty": "L2"},
                {"id": "gg_s2_fill_in_blank_018", "type": "fill_in_blank", "question": "The famous novel was written _____ Mark Twain.", "options": ["from", "by", "of", "with"], "answer_index": 1, "difficulty": "L2"},
                {"id": "gg_s2_fill_in_blank_019", "type": "fill_in_blank", "question": "I will call you as soon as I _____ at the station.", "options": ["arriving", "arrived", "arrive", "will arrive"], "answer_index": 2, "difficulty": "L2"},
                {"id": "gg_s2_fill_in_blank_020", "type": "fill_in_blank", "question": "Unless you _____ hard, you will fail the exam.", "options": ["don't study", "will study", "studied", "study"], "answer_index": 3, "difficulty": "L2"},
                {"id": "gg_s2_fill_in_blank_021", "type": "fill_in_blank", "question": "If I _____ a bird, I would fly across the ocean.", "options": ["were", "am", "be", "was"], "answer_index": 0, "difficulty": "L2"},
                {"id": "gg_s2_fill_in_blank_022", "type": "fill_in_blank", "question": "Neither of the boys _____ here right now.", "options": ["were", "is", "be", "are"], "answer_index": 1, "difficulty": "L2"},
                {"id": "gg_s2_fill_in_blank_023", "type": "fill_in_blank", "question": "Each of the students _____ a unique textbook.", "options": ["having", "are", "has", "have"], "answer_index": 2, "difficulty": "L2"},
                {"id": "gg_s2_fill_in_blank_024", "type": "fill_in_blank", "question": "Please be quiet; she _____ television right now.", "options": ["watched", "watch", "watches", "is watching"], "answer_index": 3, "difficulty": "L2"},
                {"id": "gg_s2_fill_in_blank_025", "type": "fill_in_blank", "question": "I usually _____ up at 7 AM on weekdays.", "options": ["wake", "woke", "wakes", "am waking"], "answer_index": 0, "difficulty": "L2"},
                {"id": "gg_s2_fill_in_blank_026", "type": "fill_in_blank", "question": "He accidentally cut _____ with a sharp knife.", "options": ["him", "himself", "his", "he"], "answer_index": 1, "difficulty": "L2"},
                {"id": "gg_s2_fill_in_blank_027", "type": "fill_in_blank", "question": "We really enjoyed _____ at the birthday party.", "options": ["our", "we", "ourselves", "us"], "answer_index": 2, "difficulty": "L2"},
                {"id": "gg_s2_fill_in_blank_028", "type": "fill_in_blank", "question": "This is the exact house _____ Jack built.", "options": ["what", "who", "whom", "that"], "answer_index": 3, "difficulty": "L2"},
                {"id": "gg_s2_fill_in_blank_029", "type": "fill_in_blank", "question": "The man _____ car was stolen went to the police.", "options": ["whose", "who", "who's", "whom"], "answer_index": 0, "difficulty": "L2"},
                {"id": "gg_s2_fill_in_blank_030", "type": "fill_in_blank", "question": "I have been living in this city _____ 2010.", "options": ["in", "since", "from", "for"], "answer_index": 1, "difficulty": "L2"},
                {"id": "gg_s2_fill_in_blank_031", "type": "fill_in_blank", "question": "She has worked at the company _____ five years.", "options": ["since", "until", "for", "during"], "answer_index": 2, "difficulty": "L2"},
                {"id": "gg_s2_fill_in_blank_032", "type": "fill_in_blank", "question": "Despite _____ tired, he kept working on the project.", "options": ["was", "be", "is", "being"], "answer_index": 3, "difficulty": "L2"},
                {"id": "gg_s2_fill_in_blank_033", "type": "fill_in_blank", "question": "You had _____ see a doctor about that cough.", "options": ["better", "must", "rather", "should"], "answer_index": 0, "difficulty": "L2"},
                {"id": "gg_s2_fill_in_blank_034", "type": "fill_in_blank", "question": "Would you mind _____ the window, please?", "options": ["to open", "opening", "open", "opened"], "answer_index": 1, "difficulty": "L2"},
                {"id": "gg_s2_synonym_035", "type": "synonym", "question": "Which word means the same as 'difficult'?", "options": ["simple", "hard", "easy", "clear"], "answer_index": 1, "difficulty": "L2"},
                {"id": "gg_s2_synonym_036", "type": "synonym", "question": "Which word means the same as 'huge'?", "options": ["tiny", "compact", "slight", "enormous"], "answer_index": 3, "difficulty": "L2"},
                {"id": "gg_s2_synonym_037", "type": "synonym", "question": "Which word means the same as 'fast'?", "options": ["lazy", "crawling", "rapid", "sluggish"], "answer_index": 2, "difficulty": "L2"},
                {"id": "gg_s2_synonym_038", "type": "synonym", "question": "Which word means the same as 'rich'?", "options": ["wealthy", "poor", "needy", "broke"], "answer_index": 0, "difficulty": "L2"},
                {"id": "gg_s2_synonym_039", "type": "synonym", "question": "Which word means the same as 'angry'?", "options": ["peaceful", "calm", "furious", "glad"], "answer_index": 2, "difficulty": "L2"},
                {"id": "gg_s2_synonym_040", "type": "synonym", "question": "Which word means the same as 'tired'?", "options": ["lively", "exhausted", "active", "energetic"], "answer_index": 1, "difficulty": "L2"},
                {"id": "gg_s2_synonym_041", "type": "synonym", "question": "Which word means the same as 'funny'?", "options": ["serious", "boring", "sad", "hilarious"], "answer_index": 3, "difficulty": "L2"},
                {"id": "gg_s2_synonym_042", "type": "synonym", "question": "Which word means the same as 'old'?", "options": ["ancient", "new", "recent", "modern"], "answer_index": 0, "difficulty": "L2"},
                {"id": "gg_s2_synonym_043", "type": "synonym", "question": "Which word means the same as 'cold'?", "options": ["mild", "freezing", "boiling", "warm"], "answer_index": 1, "difficulty": "L2"},
                {"id": "gg_s2_synonym_044", "type": "synonym", "question": "Which word means the same as 'hot'?", "options": ["freezing", "chilly", "cool", "boiling"], "answer_index": 3, "difficulty": "L2"},
                {"id": "gg_s2_synonym_045", "type": "synonym", "question": "Which word means the same as 'clean'?", "options": ["messy", "filthy", "spotless", "dirty"], "answer_index": 2, "difficulty": "L2"},
                {"id": "gg_s2_synonym_046", "type": "synonym", "question": "Which word means the same as 'bad'?", "options": ["terrible", "wonderful", "excellent", "great"], "answer_index": 0, "difficulty": "L2"},
                {"id": "gg_s2_synonym_047", "type": "synonym", "question": "Which word means the same as 'good'?", "options": ["terrible", "awful", "excellent", "poor"], "answer_index": 2, "difficulty": "L2"},
                {"id": "gg_s2_synonym_048", "type": "synonym", "question": "Which word means the same as 'small'?", "options": ["giant", "tiny", "large", "massive"], "answer_index": 1, "difficulty": "L2"},
                {"id": "gg_s2_synonym_049", "type": "synonym", "question": "Which word means the same as 'quiet'?", "options": ["noisy", "loud", "deafening", "silent"], "answer_index": 3, "difficulty": "L2"},
                {"id": "gg_s2_synonym_050", "type": "synonym", "question": "Which word means the same as 'brave'?", "options": ["courageous", "fearful", "timid", "scared"], "answer_index": 0, "difficulty": "L2"},
                {"id": "gg_s2_synonym_051", "type": "synonym", "question": "Which word means the same as 'smart'?", "options": ["slow", "intelligent", "foolish", "dense"], "answer_index": 1, "difficulty": "L2"},
                {"id": "gg_s2_synonym_052", "type": "synonym", "question": "Which word means the same as 'stupid'?", "options": ["brilliant", "wise", "clever", "foolish"], "answer_index": 3, "difficulty": "L2"},
                {"id": "gg_s2_synonym_053", "type": "synonym", "question": "Which word means the same as 'beautiful'?", "options": ["plain", "hideous", "gorgeous", "ugly"], "answer_index": 2, "difficulty": "L2"},
                {"id": "gg_s2_synonym_054", "type": "synonym", "question": "Which word means the same as 'ugly'?", "options": ["hideous", "pretty", "attractive", "stunning"], "answer_index": 0, "difficulty": "L2"},
                {"id": "gg_s2_synonym_055", "type": "synonym", "question": "Which word means the same as 'happy'?", "options": ["depressed", "delighted", "miserable", "sad"], "answer_index": 1, "difficulty": "L2"},
                {"id": "gg_s2_synonym_056", "type": "synonym", "question": "Which word means the same as 'sad'?", "options": ["glad", "cheerful", "joyful", "miserable"], "answer_index": 3, "difficulty": "L2"},
                {"id": "gg_s2_synonym_057", "type": "synonym", "question": "Which word means the same as 'sure'?", "options": ["doubtful", "unsure", "certain", "hesitant"], "answer_index": 2, "difficulty": "L2"},
                {"id": "gg_s2_synonym_058", "type": "synonym", "question": "Which word means the same as 'dangerous'?", "options": ["risky", "secure", "protected", "safe"], "answer_index": 0, "difficulty": "L2"},
                {"id": "gg_s2_synonym_059", "type": "synonym", "question": "Which word means the same as 'safe'?", "options": ["hazardous", "secure", "risky", "perilous"], "answer_index": 1, "difficulty": "L2"},
                {"id": "gg_s2_synonym_060", "type": "synonym", "question": "Which word means the same as 'wrong'?", "options": ["right", "accurate", "true", "incorrect"], "answer_index": 3, "difficulty": "L2"},
                {"id": "gg_s2_synonym_061", "type": "synonym", "question": "Which word means the same as 'right'?", "options": ["mistaken", "false", "correct", "wrong"], "answer_index": 2, "difficulty": "L2"},
                {"id": "gg_s2_synonym_062", "type": "synonym", "question": "Which word means the same as 'start'?", "options": ["begin", "finish", "end", "conclude"], "answer_index": 0, "difficulty": "L2"},
                {"id": "gg_s2_synonym_063", "type": "synonym", "question": "Which word means the same as 'stop'?", "options": ["continue", "cease", "start", "proceed"], "answer_index": 1, "difficulty": "L2"},
                {"id": "gg_s2_synonym_064", "type": "synonym", "question": "Which word means the same as 'help'?", "options": ["prevent", "block", "hinder", "assist"], "answer_index": 3, "difficulty": "L2"},
                {"id": "gg_s2_synonym_065", "type": "synonym", "question": "Which word means the same as 'show'?", "options": ["hide", "cover", "display", "conceal"], "answer_index": 2, "difficulty": "L2"},
                {"id": "gg_s2_synonym_066", "type": "synonym", "question": "Which word means the same as 'hide'?", "options": ["conceal", "reveal", "show", "expose"], "answer_index": 0, "difficulty": "L2"},
                {"id": "gg_s2_synonym_067", "type": "synonym", "question": "Which word means the same as 'build'?", "options": ["demolish", "construct", "destroy", "ruin"], "answer_index": 1, "difficulty": "L2"},
                {"id": "gg_s2_antonym_068", "type": "antonym", "question": "What is the opposite of 'difficult'?", "options": ["complex", "hard", "easy", "tough"], "answer_index": 2, "difficulty": "L2"},
                {"id": "gg_s2_antonym_069", "type": "antonym", "question": "What is the opposite of 'deep'?", "options": ["shallow", "profound", "low", "bottomless"], "answer_index": 0, "difficulty": "L2"},
                {"id": "gg_s2_antonym_070", "type": "antonym", "question": "What is the opposite of 'wide'?", "options": ["expansive", "broad", "thick", "narrow"], "answer_index": 3, "difficulty": "L2"},
                {"id": "gg_s2_antonym_071", "type": "antonym", "question": "What is the opposite of 'thick'?", "options": ["solid", "thin", "dense", "heavy"], "answer_index": 1, "difficulty": "L2"},
                {"id": "gg_s2_antonym_072", "type": "antonym", "question": "What is the opposite of 'heavy'?", "options": ["light", "massive", "weighty", "dense"], "answer_index": 0, "difficulty": "L2"},
                {"id": "gg_s2_antonym_073", "type": "antonym", "question": "What is the opposite of 'expensive'?", "options": ["costly", "valuable", "cheap", "pricey"], "answer_index": 2, "difficulty": "L2"},
                {"id": "gg_s2_antonym_074", "type": "antonym", "question": "What is the opposite of 'modern'?", "options": ["new", "ancient", "contemporary", "current"], "answer_index": 1, "difficulty": "L2"},
                {"id": "gg_s2_antonym_075", "type": "antonym", "question": "What is the opposite of 'public'?", "options": ["common", "shared", "open", "private"], "answer_index": 3, "difficulty": "L2"},
                {"id": "gg_s2_antonym_076", "type": "antonym", "question": "What is the opposite of 'polite'?", "options": ["respectful", "courteous", "rude", "civil"], "answer_index": 2, "difficulty": "L2"},
                {"id": "gg_s2_antonym_077", "type": "antonym", "question": "What is the opposite of 'brave'?", "options": ["cowardly", "bold", "heroic", "fearless"], "answer_index": 0, "difficulty": "L2"},
                {"id": "gg_s2_antonym_078", "type": "antonym", "question": "What is the opposite of 'smooth'?", "options": ["flat", "slick", "even", "rough"], "answer_index": 3, "difficulty": "L2"},
                {"id": "gg_s2_antonym_079", "type": "antonym", "question": "What is the opposite of 'tight'?", "options": ["secure", "loose", "snug", "firm"], "answer_index": 1, "difficulty": "L2"},
                {"id": "gg_s2_antonym_080", "type": "antonym", "question": "What is the opposite of 'empty'?", "options": ["full", "hollow", "bare", "vacant"], "answer_index": 0, "difficulty": "L2"},
                {"id": "gg_s2_antonym_081", "type": "antonym", "question": "What is the opposite of 'major'?", "options": ["huge", "crucial", "minor", "significant"], "answer_index": 2, "difficulty": "L2"},
                {"id": "gg_s2_antonym_082", "type": "antonym", "question": "What is the opposite of 'import'?", "options": ["buy", "export", "bring", "trade"], "answer_index": 1, "difficulty": "L2"},
                {"id": "gg_s2_antonym_083", "type": "antonym", "question": "What is the opposite of 'demand'?", "options": ["request", "ask", "need", "supply"], "answer_index": 3, "difficulty": "L2"},
                {"id": "gg_s2_antonym_084", "type": "antonym", "question": "What is the opposite of 'victory'?", "options": ["success", "triumph", "defeat", "win"], "answer_index": 2, "difficulty": "L2"},
                {"id": "gg_s2_antonym_085", "type": "antonym", "question": "What is the opposite of 'accept'?", "options": ["reject", "receive", "take", "allow"], "answer_index": 0, "difficulty": "L2"},
                {"id": "gg_s2_antonym_086", "type": "antonym", "question": "What is the opposite of 'remember'?", "options": ["recall", "retain", "memorize", "forget"], "answer_index": 3, "difficulty": "L2"},
                {"id": "gg_s2_antonym_087", "type": "antonym", "question": "What is the opposite of 'arrive'?", "options": ["enter", "depart", "come", "reach"], "answer_index": 1, "difficulty": "L2"},
                {"id": "gg_s2_antonym_088", "type": "antonym", "question": "What is the opposite of 'artificial'?", "options": ["natural", "synthetic", "man-made", "fake"], "answer_index": 0, "difficulty": "L2"},
                {"id": "gg_s2_antonym_089", "type": "antonym", "question": "What is the opposite of 'lazy'?", "options": ["sluggish", "idle", "active", "tired"], "answer_index": 2, "difficulty": "L2"},
                {"id": "gg_s2_antonym_090", "type": "antonym", "question": "What is the opposite of 'generous'?", "options": ["giving", "selfish", "charitable", "kind"], "answer_index": 1, "difficulty": "L2"},
                {"id": "gg_s2_antonym_091", "type": "antonym", "question": "What is the opposite of 'innocent'?", "options": ["harmless", "pure", "blameless", "guilty"], "answer_index": 3, "difficulty": "L2"},
                {"id": "gg_s2_antonym_092", "type": "antonym", "question": "What is the opposite of 'patient'?", "options": ["calm", "impatient", "understanding", "tolerant"], "answer_index": 1, "difficulty": "L2"},
                {"id": "gg_s2_antonym_093", "type": "antonym", "question": "What is the opposite of 'responsible'?", "options": ["irresponsible", "trusted", "dependable", "reliable"], "answer_index": 0, "difficulty": "L2"},
                {"id": "gg_s2_antonym_094", "type": "antonym", "question": "What is the opposite of 'visible'?", "options": ["obvious", "clear", "invisible", "seen"], "answer_index": 2, "difficulty": "L2"},
                {"id": "gg_s2_antonym_095", "type": "antonym", "question": "What is the opposite of 'possible'?", "options": ["likely", "achievable", "doable", "impossible"], "answer_index": 3, "difficulty": "L2"},
                {"id": "gg_s2_antonym_096", "type": "antonym", "question": "What is the opposite of 'logical'?", "options": ["illogical", "rational", "sound", "reasonable"], "answer_index": 0, "difficulty": "L2"},
                {"id": "gg_s2_antonym_097", "type": "antonym", "question": "What is the opposite of 'frequent'?", "options": ["common", "rare", "often", "regular"], "answer_index": 1, "difficulty": "L2"},
                {"id": "gg_s2_antonym_098", "type": "antonym", "question": "What is the opposite of 'cautious'?", "options": ["careful", "guarded", "reckless", "alert"], "answer_index": 2, "difficulty": "L2"},
                {"id": "gg_s2_antonym_099", "type": "antonym", "question": "What is the opposite of 'permanent'?", "options": ["lasting", "stable", "forever", "temporary"], "answer_index": 3, "difficulty": "L2"},
                {"id": "gg_s2_antonym_100", "type": "antonym", "question": "What is the opposite of 'ascend'?", "options": ["descend", "climb", "soar", "rise"], "answer_index": 0, "difficulty": "L2"},
                {"id": "gg_s2_plural_101", "type": "plural", "question": "What is the plural of 'half'?", "options": ["halvess", "halfes", "halfs", "halves"], "answer_index": 3, "difficulty": "L2"},
                {"id": "gg_s2_plural_102", "type": "plural", "question": "What is the plural of 'leaf'?", "options": ["leave", "leaves", "leafes", "leafs"], "answer_index": 1, "difficulty": "L2"},
                {"id": "gg_s2_plural_103", "type": "plural", "question": "What is the plural of 'thief'?", "options": ["thieves", "theives", "thiefes", "thiefs"], "answer_index": 0, "difficulty": "L2"},
                {"id": "gg_s2_plural_104", "type": "plural", "question": "What is the plural of 'wolf'?", "options": ["wolve", "wolfes", "wolves", "wolfs"], "answer_index": 2, "difficulty": "L2"},
                {"id": "gg_s2_plural_105", "type": "plural", "question": "What is the plural of 'calf'?", "options": ["calve", "calfes", "calfs", "calves"], "answer_index": 3, "difficulty": "L2"},
                {"id": "gg_s2_plural_106", "type": "plural", "question": "What is the plural of 'life'?", "options": ["live", "lives", "life", "lifes"], "answer_index": 1, "difficulty": "L2"},
                {"id": "gg_s2_plural_107", "type": "plural", "question": "What is the plural of 'wife'?", "options": ["wives", "wive", "wife", "wifes"], "answer_index": 0, "difficulty": "L2"},
                {"id": "gg_s2_plural_108", "type": "plural", "question": "What is the plural of 'hero'?", "options": ["hero's", "hero", "heroes", "heros"], "answer_index": 2, "difficulty": "L2"},
                {"id": "gg_s2_plural_109", "type": "plural", "question": "What is the plural of 'potato'?", "options": ["potatos", "potato", "potato's", "potatoes"], "answer_index": 3, "difficulty": "L2"},
                {"id": "gg_s2_plural_110", "type": "plural", "question": "What is the plural of 'tomato'?", "options": ["tomato", "tomatoes", "tomato's", "tomatos"], "answer_index": 1, "difficulty": "L2"},
                {"id": "gg_s2_plural_111", "type": "plural", "question": "What is the plural of 'volcano'?", "options": ["volcanoes", "volcano", "volcano's", "volcanos"], "answer_index": 0, "difficulty": "L2"},
                {"id": "gg_s2_plural_112", "type": "plural", "question": "What is the plural of 'echo'?", "options": ["echo's", "echo", "echoes", "echos"], "answer_index": 2, "difficulty": "L2"},
                {"id": "gg_s2_plural_113", "type": "plural", "question": "What is the plural of 'deer'?", "options": ["deeres", "deer's", "deers", "deer"], "answer_index": 3, "difficulty": "L2"},
                {"id": "gg_s2_plural_114", "type": "plural", "question": "What is the plural of 'sheep'?", "options": ["sheep's", "sheep", "sheepes", "sheeps"], "answer_index": 1, "difficulty": "L2"},
                {"id": "gg_s2_plural_115", "type": "plural", "question": "What is the plural of 'fish'?", "options": ["fish", "fish's", "fishs", "fishes"], "answer_index": 0, "difficulty": "L2"},
                {"id": "gg_s2_plural_116", "type": "plural", "question": "What is the plural of 'salmon'?", "options": ["salmon's", "salmones", "salmon", "salmons"], "answer_index": 2, "difficulty": "L2"},
                {"id": "gg_s2_plural_117", "type": "plural", "question": "What is the plural of 'trout'?", "options": ["troutes", "trouts", "trout's", "trout"], "answer_index": 3, "difficulty": "L2"},
                {"id": "gg_s2_plural_118", "type": "plural", "question": "What is the plural of 'species'?", "options": ["specie", "species", "species's", "specieses"], "answer_index": 1, "difficulty": "L2"},
                {"id": "gg_s2_plural_119", "type": "plural", "question": "What is the plural of 'series'?", "options": ["series", "serieses", "series's", "serie"], "answer_index": 0, "difficulty": "L2"},
                {"id": "gg_s2_plural_120", "type": "plural", "question": "What is the plural of 'aircraft'?", "options": ["aircraftes", "aircraft's", "aircraft", "aircrafts"], "answer_index": 2, "difficulty": "L2"},
                {"id": "gg_s2_plural_121", "type": "plural", "question": "What is the plural of 'tooth'?", "options": ["toothes", "tooths", "teeths", "teeth"], "answer_index": 3, "difficulty": "L2"},
                {"id": "gg_s2_plural_122", "type": "plural", "question": "What is the plural of 'goose'?", "options": ["goose", "geese", "geeses", "gooses"], "answer_index": 1, "difficulty": "L2"},
                {"id": "gg_s2_plural_123", "type": "plural", "question": "What is the plural of 'foot'?", "options": ["feet", "foots", "footies", "feets"], "answer_index": 0, "difficulty": "L2"},
                {"id": "gg_s2_plural_124", "type": "plural", "question": "What is the plural of 'man'?", "options": ["man's", "mans", "men", "manes"], "answer_index": 2, "difficulty": "L2"},
                {"id": "gg_s2_plural_125", "type": "plural", "question": "What is the plural of 'woman'?", "options": ["woman's", "womans", "womens", "women"], "answer_index": 3, "difficulty": "L2"},
                {"id": "gg_s2_plural_126", "type": "plural", "question": "What is the plural of 'mouse'?", "options": ["mouses", "mice", "mouse", "mices"], "answer_index": 1, "difficulty": "L2"},
                {"id": "gg_s2_plural_127", "type": "plural", "question": "What is the plural of 'louse'?", "options": ["lice", "louse", "lices", "louses"], "answer_index": 0, "difficulty": "L2"},
                {"id": "gg_s2_plural_128", "type": "plural", "question": "What is the plural of 'child'?", "options": ["childs", "childes", "children", "childrens"], "answer_index": 2, "difficulty": "L2"},
                {"id": "gg_s2_plural_129", "type": "plural", "question": "What is the plural of 'ox'?", "options": ["oxs", "oxes", "ox", "oxen"], "answer_index": 3, "difficulty": "L2"},
                {"id": "gg_s2_plural_130", "type": "plural", "question": "What is the plural of 'person'?", "options": ["peoples", "people", "person's", "persons"], "answer_index": 1, "difficulty": "L2"},
                {"id": "gg_s2_plural_131", "type": "plural", "question": "What is the plural of 'cactus'?", "options": ["cacti", "cactuses", "cactis", "cactus"], "answer_index": 0, "difficulty": "L2"},
                {"id": "gg_s2_plural_132", "type": "plural", "question": "What is the plural of 'fungus'?", "options": ["funguses", "fungis", "fungi", "fungus"], "answer_index": 2, "difficulty": "L2"},
                {"id": "gg_s2_plural_133", "type": "plural", "question": "What is the plural of 'nucleus'?", "options": ["nucleis", "nucleuses", "nucleus", "nuclei"], "answer_index": 3, "difficulty": "L2"},
                {"id": "gg_s2_plural_134", "type": "plural", "question": "What is the plural of 'syllabus'?", "options": ["syllabis", "syllabi", "syllabus", "syllabuses"], "answer_index": 1, "difficulty": "L2"},
                {"id": "gg_s2_spot_error_135", "type": "spot_error", "question": "Find the error: 'He don't know the answer.'", "options": ["know → knows", "don't → doesn't", "the → a", "answer → answers"], "answer_index": 1, "difficulty": "L2"},
                {"id": "gg_s2_spot_error_136", "type": "spot_error", "question": "Find the error: 'She goes to school on bus.'", "options": ["goes → go", "school → schools", "to → at", "on bus → by bus"], "answer_index": 3, "difficulty": "L2"},
                {"id": "gg_s2_spot_error_137", "type": "spot_error", "question": "Find the error: 'I am waiting here since morning.'", "options": ["morning → the morning", "since → for", "am waiting → have been waiting", "here → there"], "answer_index": 2, "difficulty": "L2"},
                {"id": "gg_s2_spot_error_138", "type": "spot_error", "question": "Find the error: 'He is more taller than me.'", "options": ["more taller → taller", "me → I", "than → then", "He → Him"], "answer_index": 0, "difficulty": "L2"},
                {"id": "gg_s2_spot_error_139", "type": "spot_error", "question": "Find the error: 'They was playing football.'", "options": ["playing → played", "They → Them", "was → were", "football → footballs"], "answer_index": 2, "difficulty": "L2"},
                {"id": "gg_s2_spot_error_140", "type": "spot_error", "question": "Find the error: 'I have saw that movie before.'", "options": ["movie → movies", "saw → seen", "have → has", "that → those"], "answer_index": 1, "difficulty": "L2"},
                {"id": "gg_s2_spot_error_141", "type": "spot_error", "question": "Find the error: 'She didn't went to the party.'", "options": ["party → parties", "to → at", "didn't → don't", "went → go"], "answer_index": 3, "difficulty": "L2"},
                {"id": "gg_s2_spot_error_142", "type": "spot_error", "question": "Find the error: 'One of the boy is missing.'", "options": ["boy → boys", "missing → missed", "is → are", "One → Once"], "answer_index": 0, "difficulty": "L2"},
                {"id": "gg_s2_spot_error_143", "type": "spot_error", "question": "Find the error: 'The informations are wrong.'", "options": ["The → A", "informations are → information is", "are → is", "wrong → wrongly"], "answer_index": 1, "difficulty": "L2"},
                {"id": "gg_s2_spot_error_144", "type": "spot_error", "question": "Find the error: 'He gave me an advice.'", "options": ["me → I", "gave → give", "advice → advices", "an advice → some advice"], "answer_index": 3, "difficulty": "L2"},
                {"id": "gg_s2_spot_error_145", "type": "spot_error", "question": "Find the error: 'I prefer coffee than tea.'", "options": ["coffee → coffees", "tea → teas", "than → to", "prefer → prefers"], "answer_index": 2, "difficulty": "L2"},
                {"id": "gg_s2_spot_error_146", "type": "spot_error", "question": "Find the error: 'He is very good in English.'", "options": ["in → at", "English → the English", "very → much", "good → well"], "answer_index": 0, "difficulty": "L2"},
                {"id": "gg_s2_spot_error_147", "type": "spot_error", "question": "Find the error: 'She is married with a doctor.'", "options": ["a → the", "with → to", "married → marry", "is → are"], "answer_index": 1, "difficulty": "L2"},
                {"id": "gg_s2_spot_error_148", "type": "spot_error", "question": "Find the error: 'We discussed about the problem.'", "options": ["We → Us", "discussed → discuss", "about the → the", "problem → problems"], "answer_index": 2, "difficulty": "L2"},
                {"id": "gg_s2_spot_error_149", "type": "spot_error", "question": "Find the error: 'I look forward to meet you.'", "options": ["to → for", "you → your", "look → looking", "meet → meeting"], "answer_index": 3, "difficulty": "L2"},
                {"id": "gg_s2_spot_error_150", "type": "spot_error", "question": "Find the error: 'He insisted to pay the bill.'", "options": ["to pay → on paying", "insisted → insist", "bill → bills", "the → a"], "answer_index": 0, "difficulty": "L2"},
                {"id": "gg_s2_spot_error_151", "type": "spot_error", "question": "Find the error: 'The house is building right now.'", "options": ["right now → now", "is building → is being built", "house → houses", "is → are"], "answer_index": 1, "difficulty": "L2"},
                {"id": "gg_s2_spot_error_152", "type": "spot_error", "question": "Find the error: 'I am used to wake up early.'", "options": ["am → is", "early → earlier", "used → use", "wake → waking"], "answer_index": 3, "difficulty": "L2"},
                {"id": "gg_s2_spot_error_153", "type": "spot_error", "question": "Find the error: 'Unless you do not try, you will fail.'", "options": ["will → would", "fail → failing", "do not try → try", "Unless → If"], "answer_index": 2, "difficulty": "L2"},
                {"id": "gg_s2_spot_error_154", "type": "spot_error", "question": "Find the error: 'If I will go, I will tell you.'", "options": ["will go → go", "If → Unless", "you → your", "will tell → tell"], "answer_index": 0, "difficulty": "L2"},
                {"id": "gg_s2_spot_error_155", "type": "spot_error", "question": "Find the error: 'He asked me where are you going.'", "options": ["me → I", "are you → I was", "asked → asks", "going → go"], "answer_index": 1, "difficulty": "L2"},
                {"id": "gg_s2_spot_error_156", "type": "spot_error", "question": "Find the error: 'She told to me a lie.'", "options": ["lie → lies", "She → Her", "me → I", "told to → told"], "answer_index": 3, "difficulty": "L2"},
                {"id": "gg_s2_spot_error_157", "type": "spot_error", "question": "Find the error: 'I enjoy to read books.'", "options": ["read → reading", "enjoy → enjoys", "to read → reading", "books → book"], "answer_index": 2, "difficulty": "L2"},
                {"id": "gg_s2_spot_error_158", "type": "spot_error", "question": "Find the error: 'He avoided to answer the question.'", "options": ["to answer → answering", "question → questions", "the → a", "avoided → avoid"], "answer_index": 0, "difficulty": "L2"},
                {"id": "gg_s2_spot_error_159", "type": "spot_error", "question": "Find the error: 'They succeeded to escape the maze.'", "options": ["succeeded → succeed", "to escape → in escaping", "maze → mazes", "escape → escaping"], "answer_index": 1, "difficulty": "L2"},
                {"id": "gg_s2_spot_error_160", "type": "spot_error", "question": "Find the error: 'I am afraid from wild dogs.'", "options": ["afraid → fear", "dogs → dog", "from → of", "am → is"], "answer_index": 2, "difficulty": "L2"},
                {"id": "gg_s2_spot_error_161", "type": "spot_error", "question": "Find the error: 'She was born in 15th August.'", "options": ["born → birth", "15th → 15", "was → is", "in → on"], "answer_index": 3, "difficulty": "L2"},
                {"id": "gg_s2_spot_error_162", "type": "spot_error", "question": "Find the error: 'We have been here since three years.'", "options": ["since → for", "have → has", "been → be", "years → year"], "answer_index": 0, "difficulty": "L2"},
                {"id": "gg_s2_spot_error_163", "type": "spot_error", "question": "Find the error: 'He behaves like he is the boss.'", "options": ["he → him", "like → as if", "behaves → behave", "is → are"], "answer_index": 1, "difficulty": "L2"},
                {"id": "gg_s2_spot_error_164", "type": "spot_error", "question": "Find the error: 'Despite of the rain, we played.'", "options": ["played → play", "rain → rains", "Despite of → Despite", "we → us"], "answer_index": 2, "difficulty": "L2"},
                {"id": "gg_s2_spot_error_165", "type": "spot_error", "question": "Find the error: 'Neither of them are ready yet.'", "options": ["ready → readiness", "Neither → Either", "them → they", "are → is"], "answer_index": 3, "difficulty": "L2"},
                {"id": "gg_s2_spot_error_166", "type": "spot_error", "question": "Find the error: 'The committee have decided.'", "options": ["have → has", "decided → decide", "The → A", "committee → committees"], "answer_index": 0, "difficulty": "L2"},
                {"id": "gg_s2_spot_error_167", "type": "spot_error", "question": "Find the error: 'Where you went yesterday?'", "options": ["Where → When", "you went → did you go", "yesterday → tomorrow", "went → go"], "answer_index": 1, "difficulty": "L2"},
                {"id": "gg_s2_past_tense_168", "type": "past_tense", "question": "What is the past tense of 'catch'?", "options": ["catch", "catches", "caught", "catched"], "answer_index": 2, "difficulty": "L2"},
                {"id": "gg_s2_past_tense_169", "type": "past_tense", "question": "What is the past tense of 'teach'?", "options": ["taught", "teached", "teaches", "teach"], "answer_index": 0, "difficulty": "L2"},
                {"id": "gg_s2_past_tense_170", "type": "past_tense", "question": "What is the past tense of 'bring'?", "options": ["bringed", "brings", "brang", "brought"], "answer_index": 3, "difficulty": "L2"},
                {"id": "gg_s2_past_tense_171", "type": "past_tense", "question": "What is the past tense of 'buy'?", "options": ["buys", "bought", "buy", "buyed"], "answer_index": 1, "difficulty": "L2"},
                {"id": "gg_s2_past_tense_172", "type": "past_tense", "question": "What is the past tense of 'fight'?", "options": ["fought", "fighted", "fights", "fight"], "answer_index": 0, "difficulty": "L2"},
                {"id": "gg_s2_past_tense_173", "type": "past_tense", "question": "What is the past tense of 'think'?", "options": ["thinks", "thank", "thought", "thinked"], "answer_index": 2, "difficulty": "L2"},
                {"id": "gg_s2_past_tense_174", "type": "past_tense", "question": "What is the past tense of 'fly'?", "options": ["flown", "flew", "flies", "flied"], "answer_index": 1, "difficulty": "L2"},
                {"id": "gg_s2_past_tense_175", "type": "past_tense", "question": "What is the past tense of 'grow'?", "options": ["grown", "grows", "growed", "grew"], "answer_index": 3, "difficulty": "L2"},
                {"id": "gg_s2_past_tense_176", "type": "past_tense", "question": "What is the past tense of 'know'?", "options": ["knew", "knows", "known", "knowed"], "answer_index": 0, "difficulty": "L2"},
                {"id": "gg_s2_past_tense_177", "type": "past_tense", "question": "What is the past tense of 'throw'?", "options": ["thrown", "throws", "threw", "throwed"], "answer_index": 2, "difficulty": "L2"},
                {"id": "gg_s2_past_tense_178", "type": "past_tense", "question": "What is the past tense of 'blow'?", "options": ["blows", "blew", "blown", "blowed"], "answer_index": 1, "difficulty": "L2"},
                {"id": "gg_s2_past_tense_179", "type": "past_tense", "question": "What is the past tense of 'draw'?", "options": ["drawed", "drawn", "draws", "drew"], "answer_index": 3, "difficulty": "L2"},
                {"id": "gg_s2_past_tense_180", "type": "past_tense", "question": "What is the past tense of 'drive'?", "options": ["drives", "driven", "drove", "drived"], "answer_index": 2, "difficulty": "L2"},
                {"id": "gg_s2_past_tense_181", "type": "past_tense", "question": "What is the past tense of 'ride'?", "options": ["rode", "rided", "rides", "ridden"], "answer_index": 0, "difficulty": "L2"},
                {"id": "gg_s2_past_tense_182", "type": "past_tense", "question": "What is the past tense of 'write'?", "options": ["writed", "written", "writes", "wrote"], "answer_index": 3, "difficulty": "L2"},
                {"id": "gg_s2_past_tense_183", "type": "past_tense", "question": "What is the past tense of 'rise'?", "options": ["rised", "rose", "rises", "risen"], "answer_index": 1, "difficulty": "L2"},
                {"id": "gg_s2_past_tense_184", "type": "past_tense", "question": "What is the past tense of 'wake'?", "options": ["woke", "wakes", "woken", "waked"], "answer_index": 0, "difficulty": "L2"},
                {"id": "gg_s2_past_tense_185", "type": "past_tense", "question": "What is the past tense of 'break'?", "options": ["breaked", "broken", "broke", "breaks"], "answer_index": 2, "difficulty": "L2"},
                {"id": "gg_s2_past_tense_186", "type": "past_tense", "question": "What is the past tense of 'speak'?", "options": ["speaked", "spoke", "speaks", "spoken"], "answer_index": 1, "difficulty": "L2"},
                {"id": "gg_s2_past_tense_187", "type": "past_tense", "question": "What is the past tense of 'steal'?", "options": ["steals", "stolen", "stealed", "stole"], "answer_index": 3, "difficulty": "L2"},
                {"id": "gg_s2_past_tense_188", "type": "past_tense", "question": "What is the past tense of 'choose'?", "options": ["chose", "choosed", "chooses", "chosen"], "answer_index": 0, "difficulty": "L2"},
                {"id": "gg_s2_past_tense_189", "type": "past_tense", "question": "What is the past tense of 'freeze'?", "options": ["freezes", "frozen", "froze", "freezed"], "answer_index": 2, "difficulty": "L2"},
                {"id": "gg_s2_past_tense_190", "type": "past_tense", "question": "What is the past tense of 'wear'?", "options": ["weared", "wore", "worn", "wears"], "answer_index": 1, "difficulty": "L2"},
                {"id": "gg_s2_past_tense_191", "type": "past_tense", "question": "What is the past tense of 'tear'?", "options": ["tore", "torn", "tears", "teared"], "answer_index": 0, "difficulty": "L2"},
                {"id": "gg_s2_past_tense_192", "type": "past_tense", "question": "What is the past tense of 'swear'?", "options": ["swore", "swears", "sweared", "sworn"], "answer_index": 0, "difficulty": "L2"},
                {"id": "gg_s2_past_tense_193", "type": "past_tense", "question": "What is the past tense of 'bear'?", "options": ["bears", "born", "bore", "beared"], "answer_index": 2, "difficulty": "L2"},
                {"id": "gg_s2_past_tense_194", "type": "past_tense", "question": "What is the past tense of 'begin'?", "options": ["begun", "began", "begins", "begined"], "answer_index": 1, "difficulty": "L2"},
                {"id": "gg_s2_past_tense_195", "type": "past_tense", "question": "What is the past tense of 'drink'?", "options": ["drinked", "drinks", "drunk", "drank"], "answer_index": 3, "difficulty": "L2"},
                {"id": "gg_s2_past_tense_196", "type": "past_tense", "question": "What is the past tense of 'ring'?", "options": ["rung", "ringed", "rang", "rings"], "answer_index": 2, "difficulty": "L2"},
                {"id": "gg_s2_past_tense_197", "type": "past_tense", "question": "What is the past tense of 'sing'?", "options": ["sang", "singed", "sings", "sung"], "answer_index": 0, "difficulty": "L2"},
                {"id": "gg_s2_past_tense_198", "type": "past_tense", "question": "What is the past tense of 'swim'?", "options": ["swum", "swam", "swimmed", "swims"], "answer_index": 1, "difficulty": "L2"},
                {"id": "gg_s2_past_tense_199", "type": "past_tense", "question": "What is the past tense of 'sink'?", "options": ["sinked", "sinks", "sunk", "sank"], "answer_index": 3, "difficulty": "L2"},
                {"id": "gg_s2_past_tense_200", "type": "past_tense", "question": "What is the past tense of 'shrink'?", "options": ["shrinked", "shrinks", "shrank", "shrunk"], "answer_index": 2, "difficulty": "L2"}
            ]
        }
    ]
}
}